flexmerge/__init__.py
flexmerge/merger.py
flexmerge/strategies.py
flexmerge-0.1.0.dist-info/licenses/LICENSE
flexmerge-0.1.0.dist-info/METADATA
flexmerge-0.1.0.dist-info/WHEEL
flexmerge-0.1.0.dist-info/top_level.txt
flexmerge-0.1.0.dist-info/RECORD
